noderedpy/__init__.py
noderedpy/__property__.py
noderedpy/decorator.py
noderedpy/__nodered__/__init__.py
noderedpy/__nodered__/auth.py
noderedpy/__nodered__/node.py
noderedpy/__nodered__/red.py
noderedpy/__nodered__/route.py
noderedpy/__nodered__/theme.py
noderedpy/assets/python-logo.png
noderedpy/node-red-starter/editorTheme.json
noderedpy/node-red-starter/index.js
noderedpy/node-red-starter/package.json
noderedpy/node-red-starter/route.js
noderedpy/templates/__init__.py
noderedpy/templates/template.html
noderedpy/templates/template.js
noderedpy/templates/template.json
nodered_py-0.2.12.dist-info/LICENSE
nodered_py-0.2.12.dist-info/WHEEL
nodered_py-0.2.12.dist-info/METADATA
nodered_py-0.2.12.dist-info/RECORD
