Metadata-Version: 2.1
Name: nodered.py
Version: 0.2.12
Summary: make python function to Node-RED node
Author-email: oyajiDev <this.dev.somehit@gmail.com>
Requires-Python: >=3.9
Classifier: License :: OSI Approved :: MIT License
Classifier: Operating System :: POSIX
Classifier: Operating System :: MacOS :: MacOS X
Classifier: Operating System :: Microsoft :: Windows
Classifier: Programming Language :: Python :: 3
Classifier: Programming Language :: Python :: 3.9
Classifier: Programming Language :: Python :: 3.10
Requires-Dist: psutil==5.9.5
Requires-Dist: wget==3.2
Requires-Dist: Pillow==10.0.0
Project-URL: repository, https://github.com/oyajiDev/NodeRED.py
